[
  {
    "person_id": 1,
    "action": "talking_on_phone",
    "action_name": "打电话",
    "start_time": "00:00:01.133",
    "end_time": "00:00:01.567",
    "start_seconds": 1.133,
    "end_seconds": 1.567,
    "frame_count": 11,
    "confidence": 0.88,
    "evidence": "cell phone close to head; head_dist=0.06"
  },
  {
    "person_id": 1,
    "action": "talking_on_phone",
    "action_name": "打电话",
    "start_time": "00:00:02.567",
    "end_time": "00:00:02.900",
    "start_seconds": 2.567,
    "end_seconds": 2.9,
    "frame_count": 4,
    "confidence": 0.8466,
    "evidence": "cell phone close to head; head_dist=0.07"
  },
  {
    "person_id": 1,
    "action": "talking_on_phone",
    "action_name": "打电话",
    "start_time": "00:00:05.533",
    "end_time": "00:00:06.000",
    "start_seconds": 5.533,
    "end_seconds": 6.0,
    "frame_count": 9,
    "confidence": 0.8675,
    "evidence": "cell phone close to head; head_dist=0.07"
  },
  {
    "person_id": 1,
    "action": "drinking_water",
    "action_name": "喝水",
    "start_time": "00:00:11.667",
    "end_time": "00:00:15.033",
    "start_seconds": 11.667,
    "end_seconds": 15.033,
    "frame_count": 90,
    "confidence": 0.7341,
    "evidence": "bottle close to head and wrist; head_dist=0.29, wrist_dist=0.08"
  },
  {
    "person_id": 1,
    "action": "drinking_water",
    "action_name": "喝水",
    "start_time": "00:00:16.100",
    "end_time": "00:00:17.133",
    "start_seconds": 16.1,
    "end_seconds": 17.133,
    "frame_count": 26,
    "confidence": 0.7192,
    "evidence": "bottle close to head and wrist; head_dist=0.34, wrist_dist=0.26"
  },
  {
    "person_id": 1,
    "action": "drinking_water",
    "action_name": "喝水",
    "start_time": "00:00:17.467",
    "end_time": "00:00:18.067",
    "start_seconds": 17.467,
    "end_seconds": 18.067,
    "frame_count": 16,
    "confidence": 0.7475,
    "evidence": "bottle close to head and wrist; head_dist=0.33, wrist_dist=0.12"
  },
  {
    "person_id": 1,
    "action": "drinking_water",
    "action_name": "喝水",
    "start_time": "00:00:18.867",
    "end_time": "00:00:20.300",
    "start_seconds": 18.867,
    "end_seconds": 20.3,
    "frame_count": 38,
    "confidence": 0.7074,
    "evidence": "bottle close to head and wrist; head_dist=0.31, wrist_dist=0.22"
  },
  {
    "person_id": 1,
    "action": "drinking_water",
    "action_name": "喝水",
    "start_time": "00:00:22.867",
    "end_time": "00:00:23.467",
    "start_seconds": 22.867,
    "end_seconds": 23.467,
    "frame_count": 17,
    "confidence": 0.6403,
    "evidence": "cup close to head and wrist; head_dist=0.25, wrist_dist=0.17"
  },
  {
    "person_id": 1,
    "action": "drinking_water",
    "action_name": "喝水",
    "start_time": "00:00:24.100",
    "end_time": "00:00:25.667",
    "start_seconds": 24.1,
    "end_seconds": 25.667,
    "frame_count": 27,
    "confidence": 0.7268,
    "evidence": "cup close to head and wrist; head_dist=0.30, wrist_dist=0.09"
  },
  {
    "person_id": 1,
    "action": "talking_on_phone",
    "action_name": "打电话",
    "start_time": "00:00:28.567",
    "end_time": "00:00:29.267",
    "start_seconds": 28.567,
    "end_seconds": 29.267,
    "frame_count": 22,
    "confidence": 0.9273,
    "evidence": "cell phone close to head; head_dist=0.02"
  },
  {
    "person_id": 1,
    "action": "talking_on_phone",
    "action_name": "打电话",
    "start_time": "00:00:29.633",
    "end_time": "00:00:29.967",
    "start_seconds": 29.633,
    "end_seconds": 29.967,
    "frame_count": 9,
    "confidence": 0.842,
    "evidence": "cell phone close to head; head_dist=0.04"
  },
  {
    "person_id": 1,
    "action": "drinking_water",
    "action_name": "喝水",
    "start_time": "00:00:33.700",
    "end_time": "00:00:34.167",
    "start_seconds": 33.7,
    "end_seconds": 34.167,
    "frame_count": 8,
    "confidence": 0.6843,
    "evidence": "bottle close to head and wrist; head_dist=0.34, wrist_dist=0.10"
  }
]